{
	"description": "项目配置文件",
	"packOptions": {
		"ignore": []
	},
	"setting": {
		"urlCheck": true,
		"es6": true,
		"enhance": true,
		"postcss": true,
		"preloadBackgroundData": false,
		"minified": true,
		"newFeature": true,
		"coverView": true,
		"nodeModules": false,
		"autoAudits": false,
		"showShadowRootInWxmlPanel": true,
		"scopeDataCheck": false,
		"uglifyFileName": false,
		"checkInvalidKey": true,
		"checkSiteMap": true,
		"uploadWithSourceMap": true,
		"compileHotReLoad": false,
		"babelSetting": {
			"ignore": [],
			"disablePlugins": [],
			"outputPath": ""
		},
		"useIsolateContext": true,
		"useCompilerModule": true,
		"userConfirmedUseCompilerModuleSwitch": false
	},
	"compileType": "miniprogram",
	"libVersion": "2.11.2",
	"appid": "wxc23eda9fe079b6e0",
	"projectname": "%E6%B5%8B%E8%AF%95",
	"debugOptions": {
		"hidedInDevtools": []
	},
	"isGameTourist": false,
	"simulatorType": "wechat",
	"simulatorPluginLibVersion": {},
	"condition": {
		"search": {
			"current": -1,
			"list": []
		},
		"conversation": {
			"current": -1,
			"list": []
		},
		"plugin": {
			"current": -1,
			"list": []
		},
		"game": {
			"currentL": -1,
			"list": []
		},
		"gamePlugin": {
			"current": -1,
			"list": []
		},
		"miniprogram": {
			"current": -1,
			"list": [
				{
					"id": -1,
					"name": "pages/clothes_type/clothes_type",
					"pathName": "pages/clothes_type/clothes_type",
					"query": "",
					"scene": null
				},
				{
					"id": 1,
					"name": "pages/clothes_list/clothes_list",
					"pathName": "pages/clothes_list/clothes_list",
					"query": "type=1&word=中袖",
					"scene": null
				},
				{
					"id": -1,
					"name": "pages/search/search",
					"pathName": "pages/search/search",
					"query": "",
					"scene": null
				}
			]
		}
	}
}